{
  "warnings": [
    {
      "file": "/Users/Arthur/Documents/oss/guitar/Sources/Guitar.swift",
      "line": null,
      "symbol": "Guitar",
      "symbol_kind": "source.lang.swift.decl.extension",
      "warning": "undocumented"
    },
    {
      "file": "/Users/Arthur/Documents/oss/guitar/Sources/Guitar.swift",
      "line": null,
      "symbol": "Guitar",
      "symbol_kind": "source.lang.swift.decl.extension",
      "warning": "undocumented"
    },
    {
      "file": "/Users/Arthur/Documents/oss/guitar/Sources/Guitar.swift",
      "line": null,
      "symbol": "Guitar",
      "symbol_kind": "source.lang.swift.decl.extension",
      "warning": "undocumented"
    },
    {
      "file": "/Users/Arthur/Documents/oss/guitar/Sources/Guitar.swift",
      "line": null,
      "symbol": "Guitar",
      "symbol_kind": "source.lang.swift.decl.extension",
      "warning": "undocumented"
    },
    {
      "file": "/Users/Arthur/Documents/oss/guitar/Sources/Guitar.swift",
      "line": null,
      "symbol": "Guitar",
      "symbol_kind": "source.lang.swift.decl.extension",
      "warning": "undocumented"
    },
    {
      "file": "/Users/Arthur/Documents/oss/guitar/Sources/Guitar.swift",
      "line": null,
      "symbol": "Guitar",
      "symbol_kind": "source.lang.swift.decl.extension",
      "warning": "undocumented"
    },
    {
      "file": "/Users/Arthur/Documents/oss/guitar/Sources/Guitar.swift",
      "line": null,
      "symbol": "Guitar",
      "symbol_kind": "source.lang.swift.decl.extension",
      "warning": "undocumented"
    },
    {
      "file": "/Users/Arthur/Documents/oss/guitar/Sources/Guitar.swift",
      "line": null,
      "symbol": "Guitar",
      "symbol_kind": "source.lang.swift.decl.extension",
      "warning": "undocumented"
    },
    {
      "file": "/Users/Arthur/Documents/oss/guitar/Sources/Guitar.swift",
      "line": 13,
      "symbol": "Guitar",
      "symbol_kind": "source.lang.swift.decl.struct",
      "warning": "undocumented"
    },
    {
      "file": "/Users/Arthur/Documents/oss/guitar/Sources/Guitar.swift",
      "line": 13,
      "symbol": "Guitar",
      "symbol_kind": "source.lang.swift.decl.struct",
      "warning": "undocumented"
    },
    {
      "file": "/Users/Arthur/Documents/oss/guitar/Sources/Guitar.swift",
      "line": 13,
      "symbol": "Guitar",
      "symbol_kind": "source.lang.swift.decl.struct",
      "warning": "undocumented"
    },
    {
      "file": "/Users/Arthur/Documents/oss/guitar/Sources/Guitar.swift",
      "line": 13,
      "symbol": "Guitar",
      "symbol_kind": "source.lang.swift.decl.struct",
      "warning": "undocumented"
    }
  ],
  "source_directory": "/Users/Arthur/Documents/oss/guitar"
}